python_ms_core/__init__.py
python_ms_core/version.py
python_ms_core/core/__init__.py
python_ms_core/core/auth/__init__.py
python_ms_core/core/auth/abstracts/__init__.py
python_ms_core/core/auth/abstracts/authorizer_abstract.py
python_ms_core/core/auth/models/__init__.py
python_ms_core/core/auth/models/permission_request.py
python_ms_core/core/auth/provider/__init__.py
python_ms_core/core/auth/provider/hosted/__init__.py
python_ms_core/core/auth/provider/hosted/hosted_authorizer.py
python_ms_core/core/auth/provider/simulated/__init__.py
python_ms_core/core/auth/provider/simulated/simulated_authorizer.py
python_ms_core/core/config/__init__.py
python_ms_core/core/config/config.py
python_ms_core/core/logger/__init__.py
python_ms_core/core/logger/local_logger.py
python_ms_core/core/logger/logger.py
python_ms_core/core/logger/abstracts/__init__.py
python_ms_core/core/logger/abstracts/logger_abstract.py
python_ms_core/core/queue/__init__.py
python_ms_core/core/queue/local_queue.py
python_ms_core/core/queue/queue.py
python_ms_core/core/queue/abstracts/__init__.py
python_ms_core/core/queue/abstracts/queue_abstract.py
python_ms_core/core/queue/config/__init__.py
python_ms_core/core/queue/config/queue_config.py
python_ms_core/core/queue/models/__init__.py
python_ms_core/core/queue/models/queue_message.py
python_ms_core/core/resource_errors/__init__.py
python_ms_core/core/resource_errors/errors.py
python_ms_core/core/storage/__init__.py
python_ms_core/core/storage/abstract/__init__.py
python_ms_core/core/storage/abstract/file_entity.py
python_ms_core/core/storage/abstract/storage_client.py
python_ms_core/core/storage/abstract/storage_container.py
python_ms_core/core/storage/config/__init__.py
python_ms_core/core/storage/config/storage_config.py
python_ms_core/core/storage/models/__init__.py
python_ms_core/core/storage/models/config.py
python_ms_core/core/storage/providers/__init__.py
python_ms_core/core/storage/providers/azure/__init__.py
python_ms_core_test-0.0.24.dist-info/licenses/LICENSE
python_ms_core_test-0.0.24.dist-info/METADATA
python_ms_core_test-0.0.24.dist-info/WHEEL
python_ms_core_test-0.0.24.dist-info/top_level.txt
python_ms_core_test-0.0.24.dist-info/RECORD
