Metadata-Version: 2.4
Name: python_ms_core_test
Version: 0.0.24
Summary: Python Boilerplate with cloud interaction
Home-page: https://github.com/TaskarCenterAtUW/TDEI-Python-ms-core
Author: Sujata Misra
Author-email: sujatam@gaussiansolutions.com
Project-URL: Documentation, https://github.com/TaskarCenterAtUW/TDEI-Python-ms-core/blob/main/README.md
Project-URL: GitHub, https://github.com/TaskarCenterAtUW/TDEI-Python-ms-core
Project-URL: Changelog, https://github.com/TaskarCenterAtUW/TDEI-Python-ms-core/blob/develop/CHANGELOG.md
Classifier: Programming Language :: Python :: 3
Classifier: License :: OSI Approved :: MIT License
Classifier: Operating System :: OS Independent
Requires-Python: >=3.9
License-File: LICENSE
Requires-Dist: azure-common~=1.1.28
Requires-Dist: azure-core~=1.30.1
Requires-Dist: azure-servicebus~=7.12.2
Requires-Dist: azure-storage-blob~=12.20.0
Requires-Dist: certifi~=2024.2.2
Requires-Dist: cffi~=1.16.0
Requires-Dist: charset-normalizer~=3.3.2
Requires-Dist: cryptography~=39.0.0
Requires-Dist: idna~=3.7
Requires-Dist: isodate~=0.6.1
Requires-Dist: msrest~=0.7.1
Requires-Dist: oauthlib~=3.2.2
Requires-Dist: pycparser~=2.22
Requires-Dist: python-dotenv~=1.0.1
Requires-Dist: requests~=2.31.0
Requires-Dist: requests-oauthlib~=2.0.0
Requires-Dist: six~=1.16.0
Requires-Dist: typing_extensions~=4.11.0
Requires-Dist: uamqp~=1.6.9
Requires-Dist: urllib3~=2.2.1
Requires-Dist: pika~=1.3.2
Requires-Dist: httpx~=0.27.0
Requires-Dist: coverage~=7.5.1
Requires-Dist: html_testRunner~=1.2.1
Requires-Dist: psutil~=5.9.8
Dynamic: author
Dynamic: author-email
Dynamic: classifier
Dynamic: description
Dynamic: description-content-type
Dynamic: home-page
Dynamic: license-file
Dynamic: project-url
Dynamic: requires-dist
Dynamic: requires-python
Dynamic: summary
